Metadata-Version: 2.1
Name: UPnPPort
Version: 0.1.1
Summary: Open ports in
Home-page: https://github.com/ibizaman/upnpport
Author: Pierre Penninckx
Author-email: ibizapeanut@gmail.com
License: GPLv3
Download-URL: https://github.com/ibizaman/upnpport/archive/0.1.1.tar.gz
Keywords: upnp
Platform: UNKNOWN
Provides-Extra: dev
Provides-Extra: test
